fstrider/__init__.py
fstrider/__main__.py
fstrider/clipboard.py
fstrider/fs.py
fstrider/fstrider
fstrider/fstrider.py
fstrider/os.py
fstrider/ptk.py
fstrider-0.1.21.data/scripts/fstrider
xontrib/fstrider.py
fstrider-0.1.21.dist-info/LICENSE
fstrider-0.1.21.dist-info/METADATA
fstrider-0.1.21.dist-info/WHEEL
fstrider-0.1.21.dist-info/top_level.txt
fstrider-0.1.21.dist-info/RECORD
