Metadata-Version: 2.1
Name: fstrider
Version: 0.1.21
Summary: Library of the useful macroses for the xonsh shell.
Author-email: anki-code <no@no.no>
License: MIT License
Project-URL: Homepage, https://github.com/anki-code/fstrider
Project-URL: Documentation, https://github.com/xonsh/fstrider/blob/master/README.md
Project-URL: Code, https://github.com/xonsh/fstrider
Project-URL: Issue tracker, https://github.com/xonsh/fstrider/issues
Classifier: Programming Language :: Python :: 3
Classifier: License :: OSI Approved :: MIT License
Classifier: Operating System :: OS Independent
Classifier: Topic :: System :: Shells
Classifier: Topic :: System :: System Shells
Classifier: Topic :: Terminals
Requires-Python: >=3.8
License-File: LICENSE
Requires-Dist: xonsh[full] >=0.12.5
Provides-Extra: dev
Requires-Dist: pytest >=7.0 ; extra == 'dev'
